eyja_es/__init__.py
eyja_es/es_hub.py
eyja_elasticsearch_hub-0.1.0.dist-info/METADATA
eyja_elasticsearch_hub-0.1.0.dist-info/WHEEL
eyja_elasticsearch_hub-0.1.0.dist-info/top_level.txt
eyja_elasticsearch_hub-0.1.0.dist-info/zip-safe
eyja_elasticsearch_hub-0.1.0.dist-info/RECORD
